[
  {
    "mode": "NULLABLE",
    "name": "id",
    "type": "STRING",
    "description": "The Relevant ID of the table"
  },
  {
    "mode": "NULLABLE",
    "name": "time_period",
    "type": "INTEGER",
    "description": "The time period for which the metrics apply"
  },
  {
    "mode": "NULLABLE",
    "name": "name",
    "type": "STRING",
    "description": "The name of the entity"
  },
  {
    "mode": "NULLABLE",
    "name": "country",
    "type": "STRING",
    "description": "The country where the entity is located"
  },
  {
    "mode": "NULLABLE",
    "name": "country_code",
    "type": "STRING",
    "description": "The country_code where the entity is located"
  },
  {
    "mode": "NULLABLE",
    "name": "country_code_2",
    "type": "STRING",
    "description": "The country_code where the entity is located"
  },
  {
    "mode": "NULLABLE",
    "name": "region",
    "type": "STRING",
    "description": "The region where the entity is located"
  },
  {
    "mode": "NULLABLE",
    "name": "subregion",
    "type": "STRING",
    "description": "The sub-region where the entity is located"
  },
  {
    "mode": "NULLABLE",
    "name": "coordinates",
    "type": "STRING",
    "description": "The coordinates of the entity"
  },
  {
    "mode": "NULLABLE",
    "name": "total_outputs",
    "type": "INTEGER",
    "description": "The total number of outputs in the given time period"
  },
  {
    "fields": [
      {
        "fields": [
          {
            "mode": "NULLABLE",
            "name": "total_outputs",
            "type": "INTEGER",
            "description": "Total Output Count for this OA type"
          },
          {
            "mode": "NULLABLE",
            "name": "percent",
            "type": "FLOAT",
            "description": "Percent of Outputs that are this OA type"
          }
        ],
        "mode": "NULLABLE",
        "name": "oa",
        "type": "RECORD",
        "description": "Open Access"
      },
      {
        "fields": [
          {
            "mode": "NULLABLE",
            "name": "total_outputs",
            "type": "INTEGER",
            "description": "Total Output Count for this OA type"
          },
          {
            "mode": "NULLABLE",
            "name": "percent",
            "type": "FLOAT",
            "description": "Percent of Outputs that are this OA type"
          }
        ],
        "mode": "NULLABLE",
        "name": "green",
        "type": "RECORD",
        "description": "Green OA"
      },
      {
        "fields": [
          {
            "mode": "NULLABLE",
            "name": "total_outputs",
            "type": "INTEGER",
            "description": "Total Output Count for this OA type"
          },
          {
            "mode": "NULLABLE",
            "name": "percent",
            "type": "FLOAT",
            "description": "Percent of Outputs that are this OA type"
          }
        ],
        "mode": "NULLABLE",
        "name": "gold",
        "type": "RECORD",
        "description": "Gold OA"
      },
      {
        "fields": [
          {
            "mode": "NULLABLE",
            "name": "total_outputs",
            "type": "INTEGER",
            "description": "Total Output Count for this OA type"
          },
          {
            "mode": "NULLABLE",
            "name": "percent",
            "type": "FLOAT",
            "description": "Percent of Outputs that are this OA type"
          }
        ],
        "mode": "NULLABLE",
        "name": "gold_doaj",
        "type": "RECORD",
        "description": "GOlD in doaj"
      },
      {
        "fields": [
          {
            "mode": "NULLABLE",
            "name": "total_outputs",
            "type": "INTEGER",
            "description": "Total Output Count for this OA type"
          },
          {
            "mode": "NULLABLE",
            "name": "percent",
            "type": "FLOAT",
            "description": "Percent of Outputs that are this OA type"
          }
        ],
        "mode": "NULLABLE",
        "name": "hybrid",
        "type": "RECORD",
        "description": "Hybrid OA"
      },
      {
        "fields": [
          {
            "mode": "NULLABLE",
            "name": "total_outputs",
            "type": "INTEGER",
            "description": "Total Output Count for this OA type"
          },
          {
            "mode": "NULLABLE",
            "name": "percent",
            "type": "FLOAT",
            "description": "Percent of Outputs that are this OA type"
          }
        ],
        "mode": "NULLABLE",
        "name": "bronze",
        "type": "RECORD",
        "description": "Bronze OA"
      },
      {
        "fields": [
          {
            "mode": "NULLABLE",
            "name": "total_outputs",
            "type": "INTEGER",
            "description": "Total Output Count for this OA type"
          },
          {
            "mode": "NULLABLE",
            "name": "percent",
            "type": "FLOAT",
            "description": "Percent of Outputs that are this OA type"
          }
        ],
        "mode": "NULLABLE",
        "name": "green_only",
        "type": "RECORD",
        "description": "Green Only"
      },
      {
        "fields": [
          {
            "mode": "NULLABLE",
            "name": "total_outputs",
            "type": "INTEGER",
            "description": "Total Output Count for this OA type"
          },
          {
            "mode": "NULLABLE",
            "name": "percent",
            "type": "FLOAT",
            "description": "Percent of Outputs that are this OA type"
          }
        ],
        "mode": "NULLABLE",
        "name": "publisher",
        "type": "RECORD",
        "description": "Publisher OA"
      },
      {
        "fields": [
          {
            "mode": "NULLABLE",
            "name": "label",
            "type": "STRING",
            "description": "Access Type Display Label"
          },
          {
            "mode": "NULLABLE",
            "name": "access_type",
            "type": "STRING",
            "description": "OA Access Type"
          },
          {
            "mode": "NULLABLE",
            "name": "status",
            "type": "BOOLEAN",
            "description": "TRUE / FALSE value for whether it is taling about the OA or not OA count for the oa sub-category"
          },
          {
            "mode": "NULLABLE",
            "name": "total_outputs",
            "type": "INTEGER",
            "description": "Total Outputs of this type"
          },
          {
            "mode": "NULLABLE",
            "name": "outputs_with_citations",
            "type": "INTEGER",
            "description": "Total number of citations for this type that have citations"
          },
          {
            "mode": "NULLABLE",
            "name": "outputs_without_citations",
            "type": "INTEGER",
            "description": "Total number of citations for this type that don't have citations"
          },
          {
            "fields": [
              {
                "fields": [
                  {
                    "mode": "NULLABLE",
                    "name": "total_citations",
                    "type": "INTEGER",
                    "description": "Total Number of Citataions"
                  },
                  {
                    "fields": [
                      {
                        "mode": "NULLABLE",
                        "name": "per_25th",
                        "type": "FLOAT",
                        "description": "25th Percentile"
                      },
                      {
                        "mode": "NULLABLE",
                        "name": "median",
                        "type": "FLOAT",
                        "description": "Median number of citations"
                      },
                      {
                        "mode": "NULLABLE",
                        "name": "per_90th",
                        "type": "FLOAT",
                        "description": "90th percentile"
                      },
                      {
                        "mode": "NULLABLE",
                        "name": "per_95th",
                        "type": "FLOAT",
                        "description": "95th percentile"
                      }
                    ],
                    "mode": "NULLABLE",
                    "name": "percentiles",
                    "type": "RECORD",
                    "description": "Percentile breakdown of citations"
                  }
                ],
                "mode": "NULLABLE",
                "name": "mag",
                "type": "RECORD",
                "description": "Citations coming from the MAG data source"
              },
              {
                "fields": [
                  {
                    "mode": "NULLABLE",
                    "name": "total_citations",
                    "type": "INTEGER",
                    "description": "Total Number of Citataions"
                  },
                  {
                    "fields": [
                      {
                        "mode": "NULLABLE",
                        "name": "per_25th",
                        "type": "FLOAT",
                        "description": "25th Percentile"
                      },
                      {
                        "mode": "NULLABLE",
                        "name": "median",
                        "type": "FLOAT",
                        "description": "Median number of citations"
                      },
                      {
                        "mode": "NULLABLE",
                        "name": "per_90th",
                        "type": "FLOAT",
                        "description": "90th percentile"
                      },
                      {
                        "mode": "NULLABLE",
                        "name": "per_95th",
                        "type": "FLOAT",
                        "description": "95th percentile"
                      }
                    ],
                    "mode": "NULLABLE",
                    "name": "percentiles",
                    "type": "RECORD",
                    "description": "Percentile breakdown of citations"
                  }
                ],
                "mode": "NULLABLE",
                "name": "open_citations",
                "type": "RECORD",
                "description": "Citations coming from the Open Citations data source"
              },
              {
                "fields": [
                  {
                    "mode": "NULLABLE",
                    "name": "total_citations",
                    "type": "INTEGER",
                    "description": "Total Number of Citataions"
                  },
                  {
                    "fields": [
                      {
                        "mode": "NULLABLE",
                        "name": "per_25th",
                        "type": "FLOAT",
                        "description": "25th Percentile"
                      },
                      {
                        "mode": "NULLABLE",
                        "name": "median",
                        "type": "FLOAT",
                        "description": "Median number of citations"
                      },
                      {
                        "mode": "NULLABLE",
                        "name": "per_90th",
                        "type": "FLOAT",
                        "description": "90th percentile"
                      },
                      {
                        "mode": "NULLABLE",
                        "name": "per_95th",
                        "type": "FLOAT",
                        "description": "95th percentile"
                      }
                    ],
                    "mode": "NULLABLE",
                    "name": "percentiles",
                    "type": "RECORD",
                    "description": "Percentile breakdown of citations"
                  }
                ],
                "mode": "NULLABLE",
                "name": "crossref",
                "type": "RECORD",
                "description": "Citations coming from the crossref data source"
              }
            ],
            "mode": "NULLABLE",
            "name": "citations",
            "type": "RECORD",
            "description": "Citation information"
          }
        ],
        "mode": "REPEATED",
        "name": "breakdown",
        "type": "RECORD",
        "description": "Break down"
      }
    ],
    "mode": "NULLABLE",
    "name": "access_types",
    "type": "RECORD",
    "description": "Data summarised and broken down by OA access type"
  },
  {
    "fields": [
      {
        "fields": [
          {
            "mode": "NULLABLE",
            "name": "total_citations",
            "type": "INTEGER",
            "description": "Total number of citations from this source"
          },
          {
            "mode": "NULLABLE",
            "name": "citations_per_output",
            "type": "FLOAT",
            "description": "total number of citations divided by number of outputs"
          },
          {
            "mode": "NULLABLE",
            "name": "outputs_with_citations",
            "type": "INTEGER",
            "description": "Number of outputs that have at least one citations"
          },
          {
            "mode": "NULLABLE",
            "name": "outputs_without_citations",
            "type": "INTEGER",
            "description": "Number of outputs that have no citations"
          },
          {
            "mode": "NULLABLE",
            "name": "citations_per_cited_output",
            "type": "FLOAT",
            "description": "total number of citations divided by number of outputs that have at least one citation"
          }
        ],
        "mode": "NULLABLE",
        "name": "mag",
        "type": "RECORD",
        "description": "MAG Citation data"
      },
      {
        "fields": [
          {
            "mode": "NULLABLE",
            "name": "total_citations",
            "type": "INTEGER",
            "description": "Total number of citations from this source"
          },
          {
            "mode": "NULLABLE",
            "name": "citations_per_output",
            "type": "FLOAT",
            "description": "total number of citations divided by number of outputs"
          },
          {
            "mode": "NULLABLE",
            "name": "outputs_with_citations",
            "type": "INTEGER",
            "description": "Number of outputs that have at least one citations"
          },
          {
            "mode": "NULLABLE",
            "name": "outputs_without_citations",
            "type": "INTEGER",
            "description": "Number of outputs that have no citations"
          },
          {
            "mode": "NULLABLE",
            "name": "citations_per_cited_output",
            "type": "FLOAT",
            "description": "total number of citations divided by number of outputs that have at least one citation"
          }
        ],
        "mode": "NULLABLE",
        "name": "crossref",
        "type": "RECORD",
        "description": "Crossref Citation Data"
      },
      {
        "fields": [
          {
            "mode": "NULLABLE",
            "name": "total_citations",
            "type": "INTEGER",
            "description": "Total number of citations from this source"
          },
          {
            "mode": "NULLABLE",
            "name": "citations_per_output",
            "type": "FLOAT",
            "description": "total number of citations divided by number of outputs"
          },
          {
            "mode": "NULLABLE",
            "name": "outputs_with_citations",
            "type": "INTEGER",
            "description": "Number of outputs that have at least one citations"
          },
          {
            "mode": "NULLABLE",
            "name": "outputs_without_citations",
            "type": "INTEGER",
            "description": "Number of outputs that have no citations"
          },
          {
            "mode": "NULLABLE",
            "name": "citations_per_cited_output",
            "type": "FLOAT",
            "description": "total number of citations divided by number of outputs that have at least one citation"
          }
        ],
        "mode": "NULLABLE",
        "name": "open_citations",
        "type": "RECORD",
        "description": "Open Citations citation data"
      }
    ],
    "mode": "NULLABLE",
    "name": "citations",
    "type": "RECORD",
    "description": "Breakdown of Citations"
  },
  {
    "fields": [
      {
        "mode": "NULLABLE",
        "name": "output_type",
        "type": "STRING",
        "description": "Crossref output type"
      },
      {
        "mode": "NULLABLE",
        "name": "total_outputs",
        "type": "INTEGER",
        "description": "total number of outputs of this type"
      },
      {
        "mode": "NULLABLE",
        "name": "num_oa_outputs",
        "type": "INTEGER",
        "description": "total number of OA outputs of this type"
      },
      {
        "mode": "NULLABLE",
        "name": "num_green_outputs",
        "type": "INTEGER",
        "description": "total number of green OA outputs of this type"
      },
      {
        "mode": "NULLABLE",
        "name": "num_gold_outputs",
        "type": "INTEGER",
        "description": "total number of gold OA outputs of this type"
      },
      {
        "mode": "NULLABLE",
        "name": "num_gold_just_doaj_outputs",
        "type": "INTEGER",
        "description": "total number of gold in doaj outputs of this type"
      },
      {
        "mode": "NULLABLE",
        "name": "num_hybrid_outputs",
        "type": "INTEGER",
        "description": "total number of hybrid OA outputs of this type"
      },
      {
        "mode": "NULLABLE",
        "name": "num_bronze_outputs",
        "type": "INTEGER",
        "description": "total number of hybrid OA outputs of this type"
      },
      {
        "mode": "NULLABLE",
        "name": "num_green_only_outputs",
        "type": "INTEGER",
        "description": "total number of green only outputs of this type"
      },
      {
        "fields": [
          {
            "mode": "NULLABLE",
            "name": "total_mag_citations",
            "type": "INTEGER",
            "description": "total number of citations from mag"
          },
          {
            "mode": "NULLABLE",
            "name": "total_open_citations_citations",
            "type": "INTEGER",
            "description": "total number of citations from open citations"
          },
          {
            "mode": "NULLABLE",
            "name": "total_crossref_citations",
            "type": "INTEGER",
            "description": "total number of citations from crossref"
          }
        ],
        "mode": "NULLABLE",
        "name": "citations",
        "type": "RECORD",
        "description": "Citation breakdown"
      }
    ],
    "mode": "REPEATED",
    "name": "output_types",
    "type": "RECORD",
    "description": "Data broken down by crossref output type"
  },
  {
    "fields": [
      {
        "fields": [
          {
            "mode": "NULLABLE",
            "name": "field",
            "type": "STRING",
            "description": "MAG Field name"
          },
          {
            "mode": "NULLABLE",
            "name": "total_outputs",
            "type": "INTEGER",
            "description": "number of outputs of that field"
          },
          {
            "mode": "NULLABLE",
            "name": "sum_of_scores",
            "type": "FLOAT",
            "description": "Sum of the MAG scores. A score roughly represents how strongly 0.0-1.0 each article is associated with a field"
          },
          {
            "fields": [
              {
                "fields": [
                  {
                    "mode": "NULLABLE",
                    "name": "total_citations",
                    "type": "INTEGER",
                    "description": "Total number of citations"
                  },
                  {
                    "fields": [
                      {
                        "mode": "NULLABLE",
                        "name": "per_25th",
                        "type": "FLOAT",
                        "description": "25th Percentile"
                      },
                      {
                        "mode": "NULLABLE",
                        "name": "median",
                        "type": "FLOAT",
                        "description": "Median citations"
                      },
                      {
                        "mode": "NULLABLE",
                        "name": "per_90th",
                        "type": "FLOAT",
                        "description": "90th Percentile"
                      },
                      {
                        "mode": "NULLABLE",
                        "name": "per_95th",
                        "type": "FLOAT",
                        "description": "95th Percentile"
                      }
                    ],
                    "mode": "NULLABLE",
                    "name": "percentiles",
                    "type": "RECORD",
                    "description": "Percentile Breakdown"
                  }
                ],
                "mode": "NULLABLE",
                "name": "mag",
                "type": "RECORD",
                "description": "Citation Data from MAG"
              },
              {
                "fields": [
                  {
                    "mode": "NULLABLE",
                    "name": "total_citations",
                    "type": "INTEGER",
                    "description": "Total number of citations"
                  },
                  {
                    "fields": [
                      {
                        "mode": "NULLABLE",
                        "name": "per_25th",
                        "type": "FLOAT",
                        "description": "25th Percentile"
                      },
                      {
                        "mode": "NULLABLE",
                        "name": "median",
                        "type": "FLOAT",
                        "description": "Median citations"
                      },
                      {
                        "mode": "NULLABLE",
                        "name": "per_90th",
                        "type": "FLOAT",
                        "description": "90th Percentile"
                      },
                      {
                        "mode": "NULLABLE",
                        "name": "per_95th",
                        "type": "FLOAT",
                        "description": "95th Percentile"
                      }
                    ],
                    "mode": "NULLABLE",
                    "name": "percentiles",
                    "type": "RECORD",
                    "description": "Percentile Breakdown"
                  }
                ],
                "mode": "NULLABLE",
                "name": "open_citations",
                "type": "RECORD",
                "description": "Open Citations citation data"
              },
              {
                "fields": [
                  {
                    "mode": "NULLABLE",
                    "name": "total_citations",
                    "type": "INTEGER",
                    "description": "Total number of citations"
                  },
                  {
                    "fields": [
                      {
                        "mode": "NULLABLE",
                        "name": "per_25th",
                        "type": "FLOAT",
                        "description": "25th Percentile"
                      },
                      {
                        "mode": "NULLABLE",
                        "name": "median",
                        "type": "FLOAT",
                        "description": "Median citations"
                      },
                      {
                        "mode": "NULLABLE",
                        "name": "per_90th",
                        "type": "FLOAT",
                        "description": "90th Percentile"
                      },
                      {
                        "mode": "NULLABLE",
                        "name": "per_95th",
                        "type": "FLOAT",
                        "description": "95th Percentile"
                      }
                    ],
                    "mode": "NULLABLE",
                    "name": "percentiles",
                    "type": "RECORD",
                    "description": "Percentile Breakdown"
                  }
                ],
                "mode": "NULLABLE",
                "name": "crossref",
                "type": "RECORD",
                "description": "Crossref citation data"
              }
            ],
            "mode": "NULLABLE",
            "name": "citations",
            "type": "RECORD",
            "description": "Citation breakdown"
          },
          {
            "mode": "NULLABLE",
            "name": "num_oa_outputs",
            "type": "INTEGER",
            "description": "number of OA outputs of that field"
          },
          {
            "mode": "NULLABLE",
            "name": "num_green_outputs",
            "type": "INTEGER",
            "description": "number of green OA outputs of that field"
          },
          {
            "mode": "NULLABLE",
            "name": "num_gold_outputs",
            "type": "INTEGER",
            "description": "number of gold OA outputs of that field"
          },
          {
            "mode": "NULLABLE",
            "name": "num_gold_just_doaj_outputs",
            "type": "INTEGER",
            "description": "number of gold just in doaj outputs of that field"
          },
          {
            "mode": "NULLABLE",
            "name": "num_hybrid_outputs",
            "type": "INTEGER",
            "description": "number of hybrid OA outputs of that field"
          },
          {
            "mode": "NULLABLE",
            "name": "num_bronze_outputs",
            "type": "INTEGER",
            "description": "number of bronze OA outputs of that field"
          },
          {
            "mode": "NULLABLE",
            "name": "num_green_only_outputs",
            "type": "INTEGER",
            "description": "number of green only outputs of that field"
          },
          {
            "fields": [
              {
                "mode": "NULLABLE",
                "name": "total_funded_outputs",
                "type": "INTEGER",
                "description": "number of funded outputs of that field"
              },
              {
                "mode": "NULLABLE",
                "name": "num_international_outputs",
                "type": "INTEGER",
                "description": "number of internationally funded outputs of that field"
              },
              {
                "mode": "NULLABLE",
                "name": "num_domestic_outputs",
                "type": "INTEGER",
                "description": "number of domestically funded outputs of that field"
              },
              {
                "mode": "NULLABLE",
                "name": "num_international_and_domestic_outputs",
                "type": "INTEGER",
                "description": "number of joint internationally and domestic funded outputs of that field"
              },
              {
                "mode": "NULLABLE",
                "name": "num_government_outputs",
                "type": "INTEGER",
                "description": "number of government funded outputs of that field"
              },
              {
                "mode": "NULLABLE",
                "name": "num_private_outputs",
                "type": "INTEGER",
                "description": "number of private funded outputs of that field"
              },
              {
                "mode": "NULLABLE",
                "name": "num_government_and_private_outputs",
                "type": "INTEGER",
                "description": "number of jointly governemtn and private funded outputs of that field"
              }
            ],
            "mode": "NULLABLE",
            "name": "funding",
            "type": "RECORD",
            "description": "Breakdown of Funding Data for this type"
          },
          {
            "mode": "NULLABLE",
            "name": "num_international_collaboration_outputs",
            "type": "INTEGER",
            "description": "number of internationally collaborated on outputs of that field"
          },
          {
            "mode": "NULLABLE",
            "name": "international_collaboration_with_funding_outputs",
            "type": "INTEGER",
            "description": ""
          }
        ],
        "mode": "REPEATED",
        "name": "level0",
        "type": "RECORD",
        "description": "Level0 of the MAG fields of study Hierarchy"
      }
    ],
    "mode": "NULLABLE",
    "name": "disciplines",
    "type": "RECORD",
    "description": "Discipline Breakdown"
  },
  {
    "fields": [
      {
        "mode": "NULLABLE",
        "name": "id",
        "type": "STRING",
        "description": "Repository Name"
      },
      {
        "mode": "NULLABLE",
        "name": "total_outputs",
        "type": "INTEGER",
        "description": "Total number of outputs found on that repository"
      },
      {
        "mode": "NULLABLE",
        "name": "percentage_of_all_green",
        "type": "FLOAT",
        "description": "The percentage of all green outputs linked to that specific repository"
      }
    ],
    "mode": "REPEATED",
    "name": "repositories",
    "type": "RECORD",
    "description": "Breakdown of repositories"
  },
  {
    "fields": [
      {
        "mode": "NULLABLE",
        "name": "id",
        "type": "STRING",
        "description": "ID of entity"
      },
      {
        "mode": "NULLABLE",
        "name": "total_outputs",
        "type": "INTEGER",
        "description": "total number of outputs associated with this entity"
      },
      {
        "mode": "NULLABLE",
        "name": "percentage_of_all_outputs",
        "type": "FLOAT",
        "description": "percentage of all outputs associated with this entity"
      },
      {
        "mode": "NULLABLE",
        "name": "percentage_of_all_oa",
        "type": "FLOAT",
        "description": "percentage of all OA associated with this entity"
      },
      {
        "mode": "NULLABLE",
        "name": "name",
        "type": "STRING",
        "description": "Name of the entity"
      },
      {
        "mode": "NULLABLE",
        "name": "country",
        "type": "STRING",
        "description": "Country where the entity is located"
      },
      {
        "mode": "NULLABLE",
        "name": "country_code",
        "type": "STRING",
        "description": "Country code of the country where the entity is located"
      },
      {
        "mode": "NULLABLE",
        "name": "region",
        "type": "STRING",
        "description": "Region where the entity is located"
      },
      {
        "mode": "NULLABLE",
        "name": "subregion",
        "type": "STRING",
        "description": "Sub-region where the entity is located"
      },
      {
        "mode": "NULLABLE",
        "name": "coordinates",
        "type": "STRING",
        "description": "Coordinates of where the entity is located"
      },
      {
        "mode": "NULLABLE",
        "name": "num_oa_outputs",
        "type": "INTEGER",
        "description": "total number of OA outputs associated with this entity"
      },
      {
        "mode": "NULLABLE",
        "name": "num_in_doaj",
        "type": "INTEGER",
        "description": "total number of outputs associated with this entity in doaj"
      },
      {
        "mode": "NULLABLE",
        "name": "num_green_outputs",
        "type": "INTEGER",
        "description": "total number of green OA outputs associated with this entity"
      },
      {
        "mode": "NULLABLE",
        "name": "num_gold_outputs",
        "type": "INTEGER",
        "description": "total number of gold OA outputs associated with this entity"
      },
      {
        "mode": "NULLABLE",
        "name": "num_gold_just_doaj_outputs",
        "type": "INTEGER",
        "description": "total number of gold OA outputs just in doaj associated with this entity"
      },
      {
        "mode": "NULLABLE",
        "name": "num_hybrid_outputs",
        "type": "INTEGER",
        "description": "total number of hybrid OA outputs associated with this entity"
      },
      {
        "mode": "NULLABLE",
        "name": "num_bronze_outputs",
        "type": "INTEGER",
        "description": "total number of bronze OA outputs associated with this entity"
      },
      {
        "mode": "NULLABLE",
        "name": "num_green_only_outputs",
        "type": "INTEGER",
        "description": "total number of green only outputs associated with this entity"
      },
      {
        "mode": "NULLABLE",
        "name": "num_green_only_ignoring_bronze_outputs",
        "type": "INTEGER",
        "description": "total number of green only ignoring bronze outputs associated with this entity"
      },
      {
        "mode": "NULLABLE",
        "name": "num_has_license",
        "type": "INTEGER",
        "description": "total number of outputs that have a license associated with this entity"
      },
      {
        "mode": "NULLABLE",
        "name": "num_is_cclicensed",
        "type": "INTEGER",
        "description": "total number of outputs that have a Creative Commons license associated with this entity"
      },
      {
        "fields": [
          {
            "mode": "NULLABLE",
            "name": "mag",
            "type": "INTEGER",
            "description": "Number of citations derived from MAG"
          },
          {
            "mode": "NULLABLE",
            "name": "crosssref",
            "type": "INTEGER",
            "description": "Number of citations derived from Crossref"
          },
          {
            "mode": "NULLABLE",
            "name": "open_citations",
            "type": "INTEGER",
            "description": "Number of citations derived from Open Citations"
          }
        ],
        "mode": "NULLABLE",
        "name": "citations",
        "type": "RECORD",
        "description": "Breakdown of citations across data providers"
      },
      {
        "fields": [
          {
            "mode": "NULLABLE",
            "name": "field",
            "type": "STRING",
            "description": "MAG Field Name"
          },
          {
            "mode": "NULLABLE",
            "name": "total_outputs",
            "type": "INTEGER",
            "description": "Total number of outputs linked that that field type"
          },
          {
            "mode": "NULLABLE",
            "name": "num_oa_outputs",
            "type": "INTEGER",
            "description": "Total number of oa putputs linked to that field type"
          },
          {
            "mode": "NULLABLE",
            "name": "sum_of_scores",
            "type": "FLOAT",
            "description": "Sum of the MAG scores. A score roughly represents how strongly 0.0-1.0 each article is associated with a field"
          }
        ],
        "mode": "REPEATED",
        "name": "disciplines",
        "type": "RECORD",
        "description": "Discipline breakdown"
      }
    ],
    "mode": "REPEATED",
    "name": "institutions",
    "type": "RECORD",
    "description": "Institutional Breakdown"
  },
  {
    "fields": [
      {
        "mode": "NULLABLE",
        "name": "id",
        "type": "STRING",
        "description": "ID of entity"
      },
      {
        "mode": "NULLABLE",
        "name": "total_outputs",
        "type": "INTEGER",
        "description": "total number of outputs associated with this entity"
      },
      {
        "mode": "NULLABLE",
        "name": "percentage_of_all_outputs",
        "type": "FLOAT",
        "description": "percentage of all outputs associated with this entity"
      },
      {
        "mode": "NULLABLE",
        "name": "percentage_of_all_oa",
        "type": "FLOAT",
        "description": "percentage of all OA associated with this entity"
      },
      {
        "mode": "NULLABLE",
        "name": "name",
        "type": "STRING",
        "description": "Name of the entity"
      },
      {
        "mode": "NULLABLE",
        "name": "country",
        "type": "STRING",
        "description": "Country where the entity is located"
      },
      {
        "mode": "NULLABLE",
        "name": "country_code",
        "type": "STRING",
        "description": "Country code of the country where the entity is located"
      },
      {
        "mode": "NULLABLE",
        "name": "region",
        "type": "STRING",
        "description": "Region where the entity is located"
      },
      {
        "mode": "NULLABLE",
        "name": "subregion",
        "type": "STRING",
        "description": "Sub-region where the entity is located"
      },
      {
        "mode": "NULLABLE",
        "name": "coordinates",
        "type": "STRING",
        "description": "Coordinates of where the entity is located"
      },
      {
        "mode": "NULLABLE",
        "name": "num_oa_outputs",
        "type": "INTEGER",
        "description": "total number of OA outputs associated with this entity"
      },
      {
        "mode": "NULLABLE",
        "name": "num_in_doaj",
        "type": "INTEGER",
        "description": "total number of outputs associated with this entity in doaj"
      },
      {
        "mode": "NULLABLE",
        "name": "num_green_outputs",
        "type": "INTEGER",
        "description": "total number of green OA outputs associated with this entity"
      },
      {
        "mode": "NULLABLE",
        "name": "num_gold_outputs",
        "type": "INTEGER",
        "description": "total number of gold OA outputs associated with this entity"
      },
      {
        "mode": "NULLABLE",
        "name": "num_gold_just_doaj_outputs",
        "type": "INTEGER",
        "description": "total number of gold OA outputs just in doaj associated with this entity"
      },
      {
        "mode": "NULLABLE",
        "name": "num_hybrid_outputs",
        "type": "INTEGER",
        "description": "total number of hybrid OA outputs associated with this entity"
      },
      {
        "mode": "NULLABLE",
        "name": "num_bronze_outputs",
        "type": "INTEGER",
        "description": "total number of bronze OA outputs associated with this entity"
      },
      {
        "mode": "NULLABLE",
        "name": "num_green_only_outputs",
        "type": "INTEGER",
        "description": "total number of green only outputs associated with this entity"
      },
      {
        "mode": "NULLABLE",
        "name": "num_green_only_ignoring_bronze_outputs",
        "type": "INTEGER",
        "description": "total number of green only ignoring bronze outputs associated with this entity"
      },
      {
        "mode": "NULLABLE",
        "name": "num_has_license",
        "type": "INTEGER",
        "description": "total number of outputs that have a license associated with this entity"
      },
      {
        "mode": "NULLABLE",
        "name": "num_is_cclicensed",
        "type": "INTEGER",
        "description": "total number of outputs that have a Creative Commons license associated with this entity"
      },
      {
        "fields": [
          {
            "mode": "NULLABLE",
            "name": "mag",
            "type": "INTEGER",
            "description": "Number of citations derived from MAG"
          },
          {
            "mode": "NULLABLE",
            "name": "crosssref",
            "type": "INTEGER",
            "description": "Number of citations derived from Crossref"
          },
          {
            "mode": "NULLABLE",
            "name": "open_citations",
            "type": "INTEGER",
            "description": "Number of citations derived from Open Citations"
          }
        ],
        "mode": "NULLABLE",
        "name": "citations",
        "type": "RECORD",
        "description": "Breakdown of citations across data providers"
      },
      {
        "fields": [
          {
            "mode": "NULLABLE",
            "name": "field",
            "type": "STRING",
            "description": "MAG Field Name"
          },
          {
            "mode": "NULLABLE",
            "name": "total_outputs",
            "type": "INTEGER",
            "description": "Total number of outputs linked that that field type"
          },
          {
            "mode": "NULLABLE",
            "name": "num_oa_outputs",
            "type": "INTEGER",
            "description": "Total number of oa putputs linked to that field type"
          },
          {
            "mode": "NULLABLE",
            "name": "sum_of_scores",
            "type": "FLOAT",
            "description": "Sum of the MAG scores. A score roughly represents how strongly 0.0-1.0 each article is associated with a field"
          }
        ],
        "mode": "REPEATED",
        "name": "disciplines",
        "type": "RECORD",
        "description": "Discipline breakdown"
      }
    ],
    "mode": "REPEATED",
    "name": "countries",
    "type": "RECORD",
    "description": "Countries Breakdown"
  },
  {
    "fields": [
      {
        "mode": "NULLABLE",
        "name": "id",
        "type": "STRING",
        "description": "ID of entity"
      },
      {
        "mode": "NULLABLE",
        "name": "total_outputs",
        "type": "INTEGER",
        "description": "total number of outputs associated with this entity"
      },
      {
        "mode": "NULLABLE",
        "name": "percentage_of_all_outputs",
        "type": "FLOAT",
        "description": "percentage of all outputs associated with this entity"
      },
      {
        "mode": "NULLABLE",
        "name": "percentage_of_all_oa",
        "type": "FLOAT",
        "description": "percentage of all OA associated with this entity"
      },
      {
        "mode": "NULLABLE",
        "name": "name",
        "type": "STRING",
        "description": "Name of the entity"
      },
      {
        "mode": "NULLABLE",
        "name": "country",
        "type": "STRING",
        "description": "Country where the entity is located"
      },
      {
        "mode": "NULLABLE",
        "name": "country_code",
        "type": "STRING",
        "description": "Country code of the country where the entity is located"
      },
      {
        "mode": "NULLABLE",
        "name": "region",
        "type": "STRING",
        "description": "Region where the entity is located"
      },
      {
        "mode": "NULLABLE",
        "name": "subregion",
        "type": "STRING",
        "description": "Sub-region where the entity is located"
      },
      {
        "mode": "NULLABLE",
        "name": "coordinates",
        "type": "STRING",
        "description": "Coordinates of where the entity is located"
      },
      {
        "mode": "NULLABLE",
        "name": "num_oa_outputs",
        "type": "INTEGER",
        "description": "total number of OA outputs associated with this entity"
      },
      {
        "mode": "NULLABLE",
        "name": "num_in_doaj",
        "type": "INTEGER",
        "description": "total number of outputs associated with this entity in doaj"
      },
      {
        "mode": "NULLABLE",
        "name": "num_green_outputs",
        "type": "INTEGER",
        "description": "total number of green OA outputs associated with this entity"
      },
      {
        "mode": "NULLABLE",
        "name": "num_gold_outputs",
        "type": "INTEGER",
        "description": "total number of gold OA outputs associated with this entity"
      },
      {
        "mode": "NULLABLE",
        "name": "num_gold_just_doaj_outputs",
        "type": "INTEGER",
        "description": "total number of gold OA outputs just in doaj associated with this entity"
      },
      {
        "mode": "NULLABLE",
        "name": "num_hybrid_outputs",
        "type": "INTEGER",
        "description": "total number of hybrid OA outputs associated with this entity"
      },
      {
        "mode": "NULLABLE",
        "name": "num_bronze_outputs",
        "type": "INTEGER",
        "description": "total number of bronze OA outputs associated with this entity"
      },
      {
        "mode": "NULLABLE",
        "name": "num_green_only_outputs",
        "type": "INTEGER",
        "description": "total number of green only outputs associated with this entity"
      },
      {
        "mode": "NULLABLE",
        "name": "num_green_only_ignoring_bronze_outputs",
        "type": "INTEGER",
        "description": "total number of green only ignoring bronze outputs associated with this entity"
      },
      {
        "mode": "NULLABLE",
        "name": "num_has_license",
        "type": "INTEGER",
        "description": "total number of outputs that have a license associated with this entity"
      },
      {
        "mode": "NULLABLE",
        "name": "num_is_cclicensed",
        "type": "INTEGER",
        "description": "total number of outputs that have a Creative Commons license associated with this entity"
      },
      {
        "fields": [
          {
            "mode": "NULLABLE",
            "name": "mag",
            "type": "INTEGER",
            "description": "Number of citations derived from MAG"
          },
          {
            "mode": "NULLABLE",
            "name": "crosssref",
            "type": "INTEGER",
            "description": "Number of citations derived from Crossref"
          },
          {
            "mode": "NULLABLE",
            "name": "open_citations",
            "type": "INTEGER",
            "description": "Number of citations derived from Open Citations"
          }
        ],
        "mode": "NULLABLE",
        "name": "citations",
        "type": "RECORD",
        "description": "Breakdown of citations across data providers"
      },
      {
        "fields": [
          {
            "mode": "NULLABLE",
            "name": "field",
            "type": "STRING",
            "description": "MAG Field Name"
          },
          {
            "mode": "NULLABLE",
            "name": "total_outputs",
            "type": "INTEGER",
            "description": "Total number of outputs linked that that field type"
          },
          {
            "mode": "NULLABLE",
            "name": "num_oa_outputs",
            "type": "INTEGER",
            "description": "Total number of oa putputs linked to that field type"
          },
          {
            "mode": "NULLABLE",
            "name": "sum_of_scores",
            "type": "FLOAT",
            "description": "Sum of the MAG scores. A score roughly represents how strongly 0.0-1.0 each article is associated with a field"
          }
        ],
        "mode": "REPEATED",
        "name": "disciplines",
        "type": "RECORD",
        "description": "Discipline breakdown"
      }
    ],
    "mode": "REPEATED",
    "name": "funders",
    "type": "RECORD",
    "description": "Funders Breakdown"
  },
  {
    "fields": [
      {
        "mode": "NULLABLE",
        "name": "id",
        "type": "STRING",
        "description": "ID of entity"
      },
      {
        "mode": "NULLABLE",
        "name": "total_outputs",
        "type": "INTEGER",
        "description": "total number of outputs associated with this entity"
      },
      {
        "mode": "NULLABLE",
        "name": "percentage_of_all_outputs",
        "type": "FLOAT",
        "description": "percentage of all outputs associated with this entity"
      },
      {
        "mode": "NULLABLE",
        "name": "percentage_of_all_oa",
        "type": "FLOAT",
        "description": "percentage of all OA associated with this entity"
      },
      {
        "mode": "NULLABLE",
        "name": "name",
        "type": "STRING",
        "description": "Name of the entity"
      },
      {
        "mode": "NULLABLE",
        "name": "country",
        "type": "STRING",
        "description": "Country where the entity is located"
      },
      {
        "mode": "NULLABLE",
        "name": "country_code",
        "type": "STRING",
        "description": "Country code of the country where the entity is located"
      },
      {
        "mode": "NULLABLE",
        "name": "region",
        "type": "STRING",
        "description": "Region where the entity is located"
      },
      {
        "mode": "NULLABLE",
        "name": "subregion",
        "type": "STRING",
        "description": "Sub-region where the entity is located"
      },
      {
        "mode": "NULLABLE",
        "name": "coordinates",
        "type": "STRING",
        "description": "Coordinates of where the entity is located"
      },
      {
        "mode": "NULLABLE",
        "name": "num_oa_outputs",
        "type": "INTEGER",
        "description": "total number of OA outputs associated with this entity"
      },
      {
        "mode": "NULLABLE",
        "name": "num_in_doaj",
        "type": "INTEGER",
        "description": "total number of outputs associated with this entity in doaj"
      },
      {
        "mode": "NULLABLE",
        "name": "num_green_outputs",
        "type": "INTEGER",
        "description": "total number of green OA outputs associated with this entity"
      },
      {
        "mode": "NULLABLE",
        "name": "num_gold_outputs",
        "type": "INTEGER",
        "description": "total number of gold OA outputs associated with this entity"
      },
      {
        "mode": "NULLABLE",
        "name": "num_gold_just_doaj_outputs",
        "type": "INTEGER",
        "description": "total number of gold OA outputs just in doaj associated with this entity"
      },
      {
        "mode": "NULLABLE",
        "name": "num_hybrid_outputs",
        "type": "INTEGER",
        "description": "total number of hybrid OA outputs associated with this entity"
      },
      {
        "mode": "NULLABLE",
        "name": "num_bronze_outputs",
        "type": "INTEGER",
        "description": "total number of bronze OA outputs associated with this entity"
      },
      {
        "mode": "NULLABLE",
        "name": "num_green_only_outputs",
        "type": "INTEGER",
        "description": "total number of green only outputs associated with this entity"
      },
      {
        "mode": "NULLABLE",
        "name": "num_green_only_ignoring_bronze_outputs",
        "type": "INTEGER",
        "description": "total number of green only ignoring bronze outputs associated with this entity"
      },
      {
        "mode": "NULLABLE",
        "name": "num_has_license",
        "type": "INTEGER",
        "description": "total number of outputs that have a license associated with this entity"
      },
      {
        "mode": "NULLABLE",
        "name": "num_is_cclicensed",
        "type": "INTEGER",
        "description": "total number of outputs that have a Creative Commons license associated with this entity"
      },
      {
        "fields": [
          {
            "mode": "NULLABLE",
            "name": "mag",
            "type": "INTEGER",
            "description": "Number of citations derived from MAG"
          },
          {
            "mode": "NULLABLE",
            "name": "crosssref",
            "type": "INTEGER",
            "description": "Number of citations derived from Crossref"
          },
          {
            "mode": "NULLABLE",
            "name": "open_citations",
            "type": "INTEGER",
            "description": "Number of citations derived from Open Citations"
          }
        ],
        "mode": "NULLABLE",
        "name": "citations",
        "type": "RECORD",
        "description": "Breakdown of citations across data providers"
      },
      {
        "fields": [
          {
            "mode": "NULLABLE",
            "name": "field",
            "type": "STRING",
            "description": "MAG Field Name"
          },
          {
            "mode": "NULLABLE",
            "name": "total_outputs",
            "type": "INTEGER",
            "description": "Total number of outputs linked that that field type"
          },
          {
            "mode": "NULLABLE",
            "name": "num_oa_outputs",
            "type": "INTEGER",
            "description": "Total number of oa putputs linked to that field type"
          },
          {
            "mode": "NULLABLE",
            "name": "sum_of_scores",
            "type": "FLOAT",
            "description": "Sum of the MAG scores. A score roughly represents how strongly 0.0-1.0 each article is associated with a field"
          }
        ],
        "mode": "REPEATED",
        "name": "disciplines",
        "type": "RECORD",
        "description": "Discipline breakdown"
      }
    ],
    "mode": "REPEATED",
    "name": "publishers",
    "type": "RECORD",
    "description": "Publishers Breakdown"
  },
  {
    "fields": [
      {
        "mode": "NULLABLE",
        "name": "id",
        "type": "STRING",
        "description": "ID of entity"
      },
      {
        "mode": "NULLABLE",
        "name": "total_outputs",
        "type": "INTEGER",
        "description": "total number of outputs associated with this entity"
      },
      {
        "mode": "NULLABLE",
        "name": "percentage_of_all_outputs",
        "type": "FLOAT",
        "description": "percentage of all outputs associated with this entity"
      },
      {
        "mode": "NULLABLE",
        "name": "percentage_of_all_oa",
        "type": "FLOAT",
        "description": "percentage of all OA associated with this entity"
      },
      {
        "mode": "NULLABLE",
        "name": "name",
        "type": "STRING",
        "description": "Name of the entity"
      },
      {
        "mode": "NULLABLE",
        "name": "country",
        "type": "STRING",
        "description": "Country where the entity is located"
      },
      {
        "mode": "NULLABLE",
        "name": "country_code",
        "type": "STRING",
        "description": "Country code of the country where the entity is located"
      },
      {
        "mode": "NULLABLE",
        "name": "region",
        "type": "STRING",
        "description": "Region where the entity is located"
      },
      {
        "mode": "NULLABLE",
        "name": "subregion",
        "type": "STRING",
        "description": "Sub-region where the entity is located"
      },
      {
        "mode": "NULLABLE",
        "name": "coordinates",
        "type": "STRING",
        "description": "Coordinates of where the entity is located"
      },
      {
        "mode": "NULLABLE",
        "name": "num_oa_outputs",
        "type": "INTEGER",
        "description": "total number of OA outputs associated with this entity"
      },
      {
        "mode": "NULLABLE",
        "name": "num_in_doaj",
        "type": "INTEGER",
        "description": "total number of outputs associated with this entity in doaj"
      },
      {
        "mode": "NULLABLE",
        "name": "num_green_outputs",
        "type": "INTEGER",
        "description": "total number of green OA outputs associated with this entity"
      },
      {
        "mode": "NULLABLE",
        "name": "num_gold_outputs",
        "type": "INTEGER",
        "description": "total number of gold OA outputs associated with this entity"
      },
      {
        "mode": "NULLABLE",
        "name": "num_gold_just_doaj_outputs",
        "type": "INTEGER",
        "description": "total number of gold OA outputs just in doaj associated with this entity"
      },
      {
        "mode": "NULLABLE",
        "name": "num_hybrid_outputs",
        "type": "INTEGER",
        "description": "total number of hybrid OA outputs associated with this entity"
      },
      {
        "mode": "NULLABLE",
        "name": "num_bronze_outputs",
        "type": "INTEGER",
        "description": "total number of bronze OA outputs associated with this entity"
      },
      {
        "mode": "NULLABLE",
        "name": "num_green_only_outputs",
        "type": "INTEGER",
        "description": "total number of green only outputs associated with this entity"
      },
      {
        "mode": "NULLABLE",
        "name": "num_green_only_ignoring_bronze_outputs",
        "type": "INTEGER",
        "description": "total number of green only ignoring bronze outputs associated with this entity"
      },
      {
        "mode": "NULLABLE",
        "name": "num_has_license",
        "type": "INTEGER",
        "description": "total number of outputs that have a license associated with this entity"
      },
      {
        "mode": "NULLABLE",
        "name": "num_is_cclicensed",
        "type": "INTEGER",
        "description": "total number of outputs that have a Creative Commons license associated with this entity"
      },
      {
        "fields": [
          {
            "mode": "NULLABLE",
            "name": "mag",
            "type": "INTEGER",
            "description": "Number of citations derived from MAG"
          },
          {
            "mode": "NULLABLE",
            "name": "crosssref",
            "type": "INTEGER",
            "description": "Number of citations derived from Crossref"
          },
          {
            "mode": "NULLABLE",
            "name": "open_citations",
            "type": "INTEGER",
            "description": "Number of citations derived from Open Citations"
          }
        ],
        "mode": "NULLABLE",
        "name": "citations",
        "type": "RECORD",
        "description": "Breakdown of citations across data providers"
      },
      {
        "fields": [
          {
            "mode": "NULLABLE",
            "name": "field",
            "type": "STRING",
            "description": "MAG Field Name"
          },
          {
            "mode": "NULLABLE",
            "name": "total_outputs",
            "type": "INTEGER",
            "description": "Total number of outputs linked that that field type"
          },
          {
            "mode": "NULLABLE",
            "name": "num_oa_outputs",
            "type": "INTEGER",
            "description": "Total number of oa putputs linked to that field type"
          },
          {
            "mode": "NULLABLE",
            "name": "sum_of_scores",
            "type": "FLOAT",
            "description": "Sum of the MAG scores. A score roughly represents how strongly 0.0-1.0 each article is associated with a field"
          }
        ],
        "mode": "REPEATED",
        "name": "disciplines",
        "type": "RECORD",
        "description": "Discipline breakdown"
      }
    ],
    "mode": "REPEATED",
    "name": "journals",
    "type": "RECORD",
    "description": "Journals Breakdown"
  },
  {
    "fields": [
      {
        "mode": "NULLABLE",
        "name": "source",
        "type": "STRING",
        "description": "Event Source"
      },
      {
        "mode": "NULLABLE",
        "name": "total_outputs",
        "type": "INTEGER",
        "description": "Total number of events for that source"
      },
      {
        "mode": "NULLABLE",
        "name": "num_oa_outputs",
        "type": "INTEGER",
        "description": "Total number of events for that source for OA outputs"
      },
      {
        "mode": "NULLABLE",
        "name": "num_green_outputs",
        "type": "INTEGER",
        "description": "Total number of events for that source for green OA outputs"
      },
      {
        "mode": "NULLABLE",
        "name": "num_gold_outputs",
        "type": "INTEGER",
        "description": "Total number of events for that source for gold OA outputs"
      },
      {
        "mode": "NULLABLE",
        "name": "num_gold_just_doaj_outputs",
        "type": "INTEGER",
        "description": "Total number of events for that source for gold just in doaj outputs"
      },
      {
        "mode": "NULLABLE",
        "name": "num_hybrid_outputs",
        "type": "INTEGER",
        "description": "Total number of events for that source for hybrid OA outputs"
      },
      {
        "mode": "NULLABLE",
        "name": "num_bronze_outputs",
        "type": "INTEGER",
        "description": "Total number of events for that source for bronze OA outputs"
      },
      {
        "mode": "NULLABLE",
        "name": "num_green_only_outputs",
        "type": "INTEGER",
        "description": "Total number of events for that source for green only outputs"
      }
    ],
    "mode": "REPEATED",
    "name": "events",
    "type": "RECORD",
    "description": "Events Breakdown"
  }
]
